setup.py
txampext/__init__.py
txampext/_version.py
txampext/axiomtypes.py
txampext/commandtests.py
txampext/composed.py
txampext/constraints.py
txampext/errors.py
txampext/exposed.py
txampext/jsondialect.py
txampext/multiplexing.py
txampext/nested.py
txampext/respondertests.py
txampext.egg-info/PKG-INFO
txampext.egg-info/SOURCES.txt
txampext.egg-info/dependency_links.txt
txampext.egg-info/requires.txt
txampext.egg-info/top_level.txt
txampext/test/__init__.py
txampext/test/test_axiomtypes.py
txampext/test/test_commandtests.py
txampext/test/test_composed.py
txampext/test/test_constraints.py
txampext/test/test_errors.py
txampext/test/test_exposed.py
txampext/test/test_multiplexing.py
txampext/test/test_nested.py
txampext/test/test_respondertests.py