Metadata-Version: 1.1
Name: txampext
Version: 0.0.10
Summary: Extensions to Twisted's AMP implementation
Home-page: https://github.com/lvh/txampext
Author: Laurens Van Houtven
Author-email: _@lvh.io
License: ISC
Platform: UNKNOWN
Classifier: Development Status :: 3 - Alpha
Classifier: Framework :: Twisted
Classifier: License :: OSI Approved :: ISC License (ISCL)
